wechat_mp/__init__.py
wechat_mp/client.py
wechat_mp/exceptions.py
wechat_mp/models.py
wechat_mp/utils.py
wechat_mp-1.3.0.dist-info/LICENSE
wechat_mp-1.3.0.dist-info/METADATA
wechat_mp-1.3.0.dist-info/WHEEL
wechat_mp-1.3.0.dist-info/top_level.txt
wechat_mp-1.3.0.dist-info/RECORD
