Metadata-Version: 2.1
Name: wechat-mp
Version: 1.3.0
Summary: 导出一个公众号里的所有群发图文、根据关键词搜索原创图文和导出行业模板消息示例
Home-page: https://github.com/RogerLiNing/wechat_mp
Author: Roger Lee
Author-email: 704482843@qq.com
Classifier: Programming Language :: Python :: 3
Classifier: License :: OSI Approved :: MIT License
Classifier: Operating System :: OS Independent
License-File: LICENSE
Requires-Dist: requests
Requires-Dist: pillow
Requires-Dist: openpyxl
Requires-Dist: beautifulsoup4
Requires-Dist: threadpool
Requires-Dist: tqdm
